<?xml version="1.0"?>
<!DOCTYPE hibernate-mapping PUBLIC "-//Hibernate/Hibernate Mapping DTD 3.0//EN"
"http://hibernate.sourceforge.net/hibernate-mapping-3.0.dtd">
<!-- 
    Mapping file autogenerated by MyEclipse - Hibernate Tools
-->
<hibernate-mapping>
    <class name="co.com.coomeva.sipas.core.model.sipasdb.SipRetiros" table="SIP_RETIROS" schema="SIPASDB">
        <id name="retConsecutivo" type="java.lang.Long">
            <column name="RET_CONSECUTIVO" precision="10" scale="0" />
            <generator class="assigned" />
        </id>
        <property name="retAsoNumint" type="java.lang.Long">
            <column name="RET_ASO_NUMINT" precision="17" scale="0" not-null="true" />
        </property>
        <property name="retProdCodigo" type="java.lang.Long">
            <column name="RET_PROD_CODIGO" precision="8" scale="0" />
        </property>
        <property name="retValorCapital" type="java.lang.Double">
            <column name="RET_VALOR_CAPITAL" precision="13" />
        </property>
        <property name="retValorCargo" type="java.lang.Double">
            <column name="RET_VALOR_CARGO" precision="13" />
        </property>
        <property name="retPorcAuxPerma" type="java.lang.Double">
            <column name="RET_PORC_AUX_PERMA" precision="5" />
        </property>
        <property name="retValAuxPerma" type="java.lang.Double">
            <column name="RET_VAL_AUX_PERMA" precision="13" />
        </property>
        <property name="retPorcDistPersev" type="java.lang.Double">
            <column name="RET_PORC_DIST_PERSEV" precision="5" />
        </property>
        <property name="retPorcDistMuerte" type="java.lang.Double">
            <column name="RET_PORC_DIST_MUERTE" precision="5" />
        </property>
        <property name="retValCapitalPerse" type="java.lang.Double">
            <column name="RET_VAL_CAPITAL_PERSE" precision="13" />
        </property>
        <property name="retValCapitalMuerte" type="java.lang.Double">
            <column name="RET_VAL_CAPITAL_MUERTE" precision="13" />
        </property>
        <property name="retDebPerseverancia" type="java.lang.Double">
            <column name="RET_DEB_PERSEVERANCIA" precision="13" />
        </property>
        <property name="retDebMuerte" type="java.lang.Double">
            <column name="RET_DEB_MUERTE" precision="13" />
        </property>
        <property name="retTrasladCapPerse" type="java.lang.Double">
            <column name="RET_TRASLAD_CAP_PERSE" precision="13" />
        </property>
        <property name="retTrasladCapMuerte" type="java.lang.Double">
            <column name="RET_TRASLAD_CAP_MUERTE" precision="13" />
        </property>
        <property name="retEstado" type="java.lang.Long">
            <column name="RET_ESTADO" precision="1" scale="0" />
        </property>
        <property name="retFechaRegistro" type="java.util.Date">
            <column name="RET_FECHA_REGISTRO" length="10" />
        </property>
        <property name="retConcepto" type="java.lang.String">
            <column name="RET_CONCEPTO" length="20" />
        </property>
        <property name="retProdDisminuido" type="java.lang.String">
            <column name="RET_PROD_DISMINUIDO" length="1" />
        </property>
    </class>
</hibernate-mapping>
